{
  "type": "Feature",
  "properties": {},
  "geometry": {
    "type": "Polygon",
    "coordinates": [
      [
        [45.106567, 42.523027],
        [45.106567, 42.73854],
        [45.239502, 42.73854],
        [45.239502, 42.523027],
        [45.106567, 42.523027]
      ]
    ]
  },
  "targets_number": 3,
  "targets_coords": [
    { "latitude": 42.65012181368025, "longitude": 45.15724182128907 },
    { "latitude": 42.62537037273313, "longitude": 45.19157409667969 },
    { "latitude": 42.58594981115061, "longitude": 45.168914794921875 }
  ]
}
